<annotation>
    <folder>training_set</folder>
    <filename>20180816_171535.jpg</filename>
    <size>
        <width>4032</width>
        <height>3024</height>
        <depth>3</depth>
    </size>
    <segmented>0</segmented>
    <object>
        <name>bird</name>
        <pose>Unspecified</pose>
        <truncated>0</truncated>
        <occluded>0</occluded>
        <difficult>0</difficult>
        <polygon>
            <x1>2854</x1>
            <y1>2088</y1>
            <x2>2669</x2>
            <y2>620</y2>
            <x3>2693</x3>
            <y3>577</y3>
            <x4>2747</x4>
            <y4>587</y4>
            <x5>2771</x5>
            <y5>575</y5>
            <x6>2860</x6>
            <y6>574</y6>
            <x7>2885</x7>
            <y7>533</y7>
            <x8>2861</x8>
            <y8>495</y8>
            <x9>2762</x9>
            <y9>490</y9>
            <x10>2752</x10>
            <y10>485</y10>
            <x11>2690</x11>
            <y11>491</y11>
            <x12>2683</x12>
            <y12>498</y12>
            <x13>2534</x13>
            <y13>505</y13>
            <x14>2504</x14>
            <y14>525</y14>
            <x15>2506</x15>
            <y15>558</y15>
            <x16>2521</x16>
            <y16>569</y16>
            <x17>2549</x17>
            <y17>572</y17>
            <x18>2728</x18>
            <y18>1917</y18>
            <x19>2663</x19>
            <y19>1977</y19>
            <x20>2643</x20>
            <y20>1982</y20>
            <x21>2543</x21>
            <y21>2051</y21>
            <x22>2501</x22>
            <y22>2088</y22>
            <x23>2465</x23>
            <y23>2107</y23>
            <x24>2426</x24>
            <y24>2121</y24>
            <x25>2375</x25>
            <y25>2121</y25>
            <x26>1802</x26>
            <y26>2073</y26>
            <x27>1691</x27>
            <y27>2072</y27>
            <x28>1665</x28>
            <y28>2021</y28>
            <x29>1623</x29>
            <y29>1981</y29>
            <x30>1566</x30>
            <y30>1951</y30>
            <x31>1474</x31>
            <y31>1944</y31>
            <x32>1413</x32>
            <y32>1968</y32>
            <x33>1360</x33>
            <y33>2014</y33>
            <x34>1370</x34>
            <y34>2027</y34>
            <x35>1408</x35>
            <y35>2034</y35>
            <x36>1376</x36>
            <y36>2070</y36>
            <x37>1359</x37>
            <y37>2123</y37>
            <x38>1368</x38>
            <y38>2175</y38>
            <x39>1400</x39>
            <y39>2227</y39>
            <x40>1440</x40>
            <y40>2262</y40>
            <x41>1539</x41>
            <y41>2288</y41>
            <x42>1588</x42>
            <y42>2271</y42>
            <x43>1635</x43>
            <y43>2243</y43>
            <x44>1652</x44>
            <y44>2214</y44>
            <x45>2392</x45>
            <y45>2279</y45>
            <x46>2468</x46>
            <y46>2271</y46>
            <x47>2534</x47>
            <y47>2239</y47>
            <x48>2710</x48>
            <y48>2089</y48>
            <x49>2710</x49>
            <y49>2061</y49>
            <x50>2746</x50>
            <y50>2035</y50>
            <x51>2757</x51>
            <y51>2092</y51>
            <x52>2744</x52>
            <y52>2139</y52>
            <x53>2693</x53>
            <y53>2174</y53>
            <x54>2673</x54>
            <y54>2213</y54>
            <x55>2657</x55>
            <y55>2282</y55>
            <x56>2657</x56>
            <y56>2316</y56>
            <x57>2673</x57>
            <y57>2329</y57>
            <x58>2705</x58>
            <y58>2390</y58>
            <x59>2750</x59>
            <y59>2417</y59>
            <x60>2808</x60>
            <y60>2442</y60>
            <x61>2870</x61>
            <y61>2424</y61>
            <x62>2933</x62>
            <y62>2387</y62>
            <x63>2977</x63>
            <y63>2326</y63>
            <x64>2993</x64>
            <y64>2258</y64>
            <x65>2979</x65>
            <y65>2195</y65>
            <x66>2951</x66>
            <y66>2160</y66>
            <x67>2951</x67>
            <y67>2144</y67>
            <x68>2910</x68>
            <y68>2115</y68>
            <x69>2860</x69>
            <y69>2101</y69>
        </polygon>
    </object>
</annotation>